CHANGELOG.md
LICENSE
MANIFEST.in
Makefile
README.md
setup.cfg
setup.py
tox.ini
tests/test_middleware.py
tests/test_resolver.py
wc_django_utm.egg-info/PKG-INFO
wc_django_utm.egg-info/SOURCES.txt
wc_django_utm.egg-info/dependency_links.txt
wc_django_utm.egg-info/requires.txt
wc_django_utm.egg-info/top_level.txt
wcd_utm/__init__.py
wcd_utm/apps.py
wcd_utm/conf.py
wcd_utm/middleware.py
wcd_utm/resolver.py
wcd_utm/session_storage.py
wcd_utm/shortcuts.py
wcd_utm/locale/af/LC_MESSAGES/django.mo
wcd_utm/locale/af/LC_MESSAGES/django.po
wcd_utm/locale/ar/LC_MESSAGES/django.mo
wcd_utm/locale/ar/LC_MESSAGES/django.po
wcd_utm/locale/ast/LC_MESSAGES/django.mo
wcd_utm/locale/ast/LC_MESSAGES/django.po
wcd_utm/locale/az/LC_MESSAGES/django.mo
wcd_utm/locale/az/LC_MESSAGES/django.po
wcd_utm/locale/be/LC_MESSAGES/django.mo
wcd_utm/locale/be/LC_MESSAGES/django.po
wcd_utm/locale/bg/LC_MESSAGES/django.mo
wcd_utm/locale/bg/LC_MESSAGES/django.po
wcd_utm/locale/bn/LC_MESSAGES/django.mo
wcd_utm/locale/bn/LC_MESSAGES/django.po
wcd_utm/locale/br/LC_MESSAGES/django.mo
wcd_utm/locale/br/LC_MESSAGES/django.po
wcd_utm/locale/bs/LC_MESSAGES/django.mo
wcd_utm/locale/bs/LC_MESSAGES/django.po
wcd_utm/locale/ca/LC_MESSAGES/django.mo
wcd_utm/locale/ca/LC_MESSAGES/django.po
wcd_utm/locale/cs/LC_MESSAGES/django.mo
wcd_utm/locale/cs/LC_MESSAGES/django.po
wcd_utm/locale/cy/LC_MESSAGES/django.mo
wcd_utm/locale/cy/LC_MESSAGES/django.po
wcd_utm/locale/da/LC_MESSAGES/django.mo
wcd_utm/locale/da/LC_MESSAGES/django.po
wcd_utm/locale/de/LC_MESSAGES/django.mo
wcd_utm/locale/de/LC_MESSAGES/django.po
wcd_utm/locale/dsb/LC_MESSAGES/django.mo
wcd_utm/locale/dsb/LC_MESSAGES/django.po
wcd_utm/locale/el/LC_MESSAGES/django.mo
wcd_utm/locale/el/LC_MESSAGES/django.po
wcd_utm/locale/en/LC_MESSAGES/django.mo
wcd_utm/locale/en/LC_MESSAGES/django.po
wcd_utm/locale/eo/LC_MESSAGES/django.mo
wcd_utm/locale/eo/LC_MESSAGES/django.po
wcd_utm/locale/es/LC_MESSAGES/django.mo
wcd_utm/locale/es/LC_MESSAGES/django.po
wcd_utm/locale/et/LC_MESSAGES/django.mo
wcd_utm/locale/et/LC_MESSAGES/django.po
wcd_utm/locale/eu/LC_MESSAGES/django.mo
wcd_utm/locale/eu/LC_MESSAGES/django.po
wcd_utm/locale/fa/LC_MESSAGES/django.mo
