Metadata-Version: 2.1
Name: wc-django-utm
Version: 0.1.1
Summary: UTM parameters tracker.
Author: WebCase
Author-email: info@webcase.studio
License: MIT License
Classifier: Development Status :: 2 - Pre-Alpha
Classifier: Programming Language :: Python :: 3
Classifier: Intended Audience :: Developers
Classifier: Topic :: Utilities
Classifier: License :: OSI Approved :: MIT License
Classifier: Operating System :: OS Independent
Requires-Python: >=3.6
License-File: LICENSE
Requires-Dist: px-settings<0.2.0,>=0.1.3
Provides-Extra: dev
Requires-Dist: pytest<7.0,>=6.0; extra == "dev"
Requires-Dist: pytest-mock<4.0.0,>=3.10.0; extra == "dev"
Requires-Dist: pytest-watch<5.0,>=4.2; extra == "dev"
Requires-Dist: pytest-django<5.0,>=4.3; extra == "dev"
Requires-Dist: django-environ==0.4.5; extra == "dev"
Requires-Dist: django-stubs; extra == "dev"
Requires-Dist: django<4,>=2.2; extra == "dev"
Requires-Dist: twine; extra == "dev"
